mask_times/__init__.py
mask_times/times.py
mask_times-1.0.0.dist-info/METADATA
mask_times-1.0.0.dist-info/WHEEL
mask_times-1.0.0.dist-info/entry_points.txt
mask_times-1.0.0.dist-info/top_level.txt
mask_times-1.0.0.dist-info/RECORD
