Metadata-Version: 2.1
Name: mask_times
Version: 1.0.0
Summary: mulitply func added
Author-email: GITSangWoo <dogcenta@gmail.com>
License: MIT
Requires-Python: >=3.8
